Metadata-Version: 2.1
Name: h1parser
Version: 0.2
Summary: A simple, pure Python 2.7/3.x HTTP parser
Home-page: https://github.com/nggit/h1parser
Author: nggit
Author-email: contact@anggit.com
License: MIT
Classifier: Development Status :: 5 - Production/Stable
Classifier: License :: OSI Approved :: MIT License
Classifier: Operating System :: OS Independent
License-File: LICENSE.txt
